sllim/__init__.py
sllim/check.py
sllim-0.2.2.dist-info/LICENSE
sllim-0.2.2.dist-info/METADATA
sllim-0.2.2.dist-info/WHEEL
sllim-0.2.2.dist-info/entry_points.txt
sllim-0.2.2.dist-info/RECORD
