Metadata-Version: 2.1
Name: sllim
Version: 0.2.2
Summary: Fixing the openai api
Home-page: https://github.com/kpister/sllim
Author: Kaiser Pister
Author-email: kaiser@pister.dev
Requires-Python: >=3.9
Classifier: Programming Language :: Python :: 3
Classifier: Programming Language :: Python :: 3.9
Classifier: Programming Language :: Python :: 3.10
Classifier: Programming Language :: Python :: 3.11
Requires-Dist: openai (>=1.2.0)
Requires-Dist: pyspellchecker (>=0.7.2)
Requires-Dist: tiktoken (>=0.5.1)
